perfmonitor/__init__.py
perfmonitor/gpu_stats.py
perfmonitor/gui.py
perfmonitor/libstats.py
perfmonitor/main.py
perfmonitor-0.0.6.dist-info/LICENSE.txt
perfmonitor-0.0.6.dist-info/METADATA
perfmonitor-0.0.6.dist-info/WHEEL
perfmonitor-0.0.6.dist-info/entry_points.txt
perfmonitor-0.0.6.dist-info/top_level.txt
perfmonitor-0.0.6.dist-info/RECORD
