Metadata-Version: 2.1
Name: perfmonitor
Version: 0.0.6
Summary: Performance monitor CLI for Windows: parse and display performance counter from 'psutil' and 'nvidia-smi'.
Home-page: https://github.com/loribonna/PerfMonitorCLI
Download-URL: https://github.com/loribonna/PerfMonitorCLI/archive/refs/tags/v0.0.6.zip
Author: Lorenzo Bonicelli
Author-email: loribonna@gmail.com
License: MIT
Keywords: performance,monitor,windows,cli,powershell,commandline,htop
Classifier: Development Status :: 3 - Alpha
Classifier: Intended Audience :: Developers
Classifier: Topic :: Software Development :: Build Tools
Classifier: License :: OSI Approved :: MIT License
Classifier: Programming Language :: Python :: 3
Classifier: Programming Language :: Python :: 3.7
Classifier: Programming Language :: Python :: 3.8
License-File: LICENSE.txt
Requires-Dist: psutil
Requires-Dist: termcolor
Requires-Dist: xmltodict
